{
  "actions": [
    {
      "type": "alterTable",
      "alterTable": {
        "name": "location",
        "schema": "public",
        "addColumns": [],
        "deleteColumns": [],
        "modifyColumns": [
          {
            "columnName": "teamId",
            "addNullable": true,
            "removeNullable": false,
            "changeDefault": false
          }
        ],
        "addIndexes": [
          {
            "indexName": "location_team_unique_idx",
            "elements": [
              {
                "type": 0,
                "definition": "teamId"
              }
            ],
            "type": "btree",
            "isUnique": false,
            "isPrimary": false
          }
        ],
        "deleteIndexes": [],
        "addForeignKeys": [],
        "deleteForeignKeys": [],
        "warnings": []
      }
    }
  ],
  "warnings": [],
  "migrationApiVersion": 1
}